bitllama/__init__.py
bitllama/client.py
bitllama/exceptions.py
bitllama/mining.py
bitllama/types.py
bitllama-1.0.1.dist-info/METADATA
bitllama-1.0.1.dist-info/WHEEL
bitllama-1.0.1.dist-info/top_level.txt
bitllama-1.0.1.dist-info/RECORD
