Metadata-Version: 2.1
Name: bitllama
Version: 1.0.1
Summary: Python SDK for BitLlama Protocol
Home-page: https://github.com/samthedataman/bitllama
Author: BitLlama Team
Author-email: team@bitllama.ai
Project-URL: Bug Reports, https://github.com/samthedataman/bitllama/issues
Project-URL: Source, https://github.com/samthedataman/bitllama/tree/main/packages/python-sdk
Project-URL: Documentation, https://docs.bitllama.ai/python-sdk
Project-URL: PyPI, https://pypi.org/project/bitllama/
Classifier: Development Status :: 4 - Beta
Classifier: Intended Audience :: Developers
Classifier: Topic :: Software Development :: Libraries :: Python Modules
Classifier: License :: OSI Approved :: MIT License
Classifier: Programming Language :: Python :: 3
Classifier: Programming Language :: Python :: 3.9
Classifier: Programming Language :: Python :: 3.10
Classifier: Programming Language :: Python :: 3.11
Classifier: Programming Language :: Python :: 3.12
Requires-Python: >=3.9
Requires-Dist: web3 >=6.0.0
Requires-Dist: aiohttp >=3.9.0
Requires-Dist: asyncio >=3.4.3
Requires-Dist: pydantic >=2.0.0
Requires-Dist: eth-account >=0.10.0
Requires-Dist: python-dotenv >=1.0.0
Provides-Extra: dev
Requires-Dist: pytest >=7.4.0 ; extra == 'dev'
Requires-Dist: pytest-asyncio >=0.21.0 ; extra == 'dev'
Requires-Dist: pytest-cov >=4.1.0 ; extra == 'dev'
Requires-Dist: black >=23.0.0 ; extra == 'dev'
Requires-Dist: mypy >=1.5.0 ; extra == 'dev'
Requires-Dist: flake8 >=6.0.0 ; extra == 'dev'
